setup.py
winprivilege/func.py
winprivilege.egg-info/PKG-INFO
winprivilege.egg-info/SOURCES.txt
winprivilege.egg-info/dependency_links.txt
winprivilege.egg-info/requires.txt
winprivilege.egg-info/top_level.txt